Workbook

Sheet Executive Summary
A1: Grant Portfolio — Executive Summary
A2: Illustrative portfolio for demonstration purposes | Clean Air Fund India — sample analyst tracker
A4: ="Portfolio comprises "&COUNTA('Grant Tracker'!A6:A10)&" active grants worth ₹"&TEXT(SUM('Grant Tracker'!D6:D10)/10000000,"0.00")&" crore. Overall utilisation is "&TEXT(SUM('Grant Tracker'!E6:E10)/SUM('Grant Tracker'!D6:D10),"0%")&". "&COUNTIF('Grant Tracker'!P6:P10,"High")&" grant(s) are high risk due to implementation or reporting delays. "&(COUNTIF('Grant Tracker'!R6:R10,"*Due*")+COUNTIF('Grant Tracker'!R6:R10,"*Overdue*"))&" report(s) are due or overdue within the current cycle." -> Portfolio comprises 5 active grants worth ₹1.72 crore. Overall utilisation is 47%. 1 grant(s) are high risk due to implementation or reporting delays. 3 report(s) are due or overdue within the current cycle.
A8: Key Figures
A9: Portfolio Value | B9: =SUM('Grant Tracker'!D6:D10) -> 17200000
A10: Total Disbursed | B10: =SUM('Grant Tracker'!E6:E10) -> 8090000
A11: Overall Utilisation | B11: =SUM('Grant Tracker'!E6:E10)/SUM('Grant Tracker'!D6:D10) -> 0.47034884
A12: Active Grants | B12: =COUNTIF('Grant Tracker'!O6:O10,"<>Completed") -> 4
A13: High-Risk Grants | B13: =COUNTIF('Grant Tracker'!P6:P10,"High") -> 1
A14: Reports Due <30 Days | B14: =COUNTIF('Grant Tracker'!R6:R10,"*Due*")+COUNTIF('Grant Tracker'!R6:R10,"*Overdue*") -> 3

Sheet Dashboard
A1: Portfolio Dashboard
A2: Clean Air Fund India — Illustrative Grant Portfolio
A4: PORTFOLIO VALUE | D4: TOTAL DISBURSED | G4: UTILISATION | J4: ACTIVE GRANTS | M4: HIGH-RISK GRANTS
A5: ='Grant Tracker'!D11 -> 17200000 | D5: ='Grant Tracker'!E11 -> 8090000 | G5: ='Grant Tracker'!G11 -> 0.47034884 | J5: =COUNTIF('Grant Tracker'!O6:O10,"<>Completed") -> 4 | M5: =COUNTIF('Grant Tracker'!P6:P10,"High") -> 1
A9: Chart Data (auto-calculated — do not delete)
A10: Grant | B10: Total Budget | C10: Disbursed | D10: Utilisation %
A11: ='Grant Tracker'!A6 -> Air Quality Monitoring | B11: ='Grant Tracker'!D6 -> 4500000 | C11: ='Grant Tracker'!E6 -> 3200000 | D11: ='Grant Tracker'!G6 -> 0.71111111
A12: ='Grant Tracker'!A7 -> City Emissions Programme | B12: ='Grant Tracker'!D7 -> 6800000 | C12: ='Grant Tracker'!E7 -> 2100000 | D12: ='Grant Tracker'!G7 -> 0.30882353
A13: ='Grant Tracker'!A8 -> CEO Clean Air Initiative | B13: ='Grant Tracker'!D8 -> 1800000 | C13: ='Grant Tracker'!E8 -> 1800000 | D13: ='Grant Tracker'!G8 -> 1
A14: ='Grant Tracker'!A9 -> Clean Air & Health Project | B14: ='Grant Tracker'!D9 -> 2900000 | C14: ='Grant Tracker'!E9 -> 950000 | D14: ='Grant Tracker'!G9 -> 0.32758621
A15: ='Grant Tracker'!A10 -> Community Awareness Campaign | B15: ='Grant Tracker'!D10 -> 1200000 | C15: ='Grant Tracker'!E10 -> 40000 | D15: ='Grant Tracker'!G10 -> 0.033333333
A17: Status | B17: Count
A18: On Track | B18: =COUNTIF('Grant Tracker'!O6:O10,"On Track") -> 2
A19: Needs Attention | B19: =COUNTIF('Grant Tracker'!O6:O10,"Needs Attention") -> 1
A20: Completed | B20: =COUNTIF('Grant Tracker'!O6:O10,"Completed") -> 1
A21: Delayed | B21: =COUNTIF('Grant Tracker'!O6:O10,"Delayed") -> 1
A23: Risk | B23: Count
A24: Low | B24: =COUNTIF('Grant Tracker'!P6:P10,"Low") -> 3
A25: Medium | B25: =COUNTIF('Grant Tracker'!P6:P10,"Medium") -> 1
A26: High | B26: =COUNTIF('Grant Tracker'!P6:P10,"High") -> 1
A28: Grant Health Score
A29: Grant | B29: Score | C29: Rating
A30: ='Grant Tracker'!A6 -> Air Quality Monitoring | B30: ='Grant Tracker'!S6 -> 100 | C30: ='Grant Tracker'!T6 -> 🟢 Green
A31: ='Grant Tracker'!A7 -> City Emissions Programme | B31: ='Grant Tracker'!S7 -> 75 | C31: ='Grant Tracker'!T7 -> 🟡 Amber
A32: ='Grant Tracker'!A8 -> CEO Clean Air Initiative | B32: ='Grant Tracker'!S8 -> 100 | C32: ='Grant Tracker'!T8 -> 🟢 Green
A33: ='Grant Tracker'!A9 -> Clean Air & Health Project | B33: ='Grant Tracker'!S9 -> 100 | C33: ='Grant Tracker'!T9 -> 🟢 Green
A34: ='Grant Tracker'!A10 -> Community Awareness Campaign | B34: ='Grant Tracker'!S10 -> 30 | C34: ='Grant Tracker'!T10 -> 🔴 Red
A37: Reporting Calendar
A38: Grant | B38: Reporting Due | C38: Status
A39: ='Grant Tracker'!A6 -> Air Quality Monitoring | B39: ='Grant Tracker'!Q6 -> 46242 | C39: ='Grant Tracker'!R6 -> 🟢 31 days remaining
A40: ='Grant Tracker'!A7 -> City Emissions Programme | B40: ='Grant Tracker'!Q7 -> 46220 | C40: ='Grant Tracker'!R7 -> 🟡 Due in 9 days
A41: ='Grant Tracker'!A8 -> CEO Clean Air Initiative | B41: ='Grant Tracker'!Q8 -> 46213 | C41: ='Grant Tracker'!R8 -> ✅ Final report submitted
A42: ='Grant Tracker'!A9 -> Clean Air & Health Project | B42: ='Grant Tracker'!Q9 -> 46270 | C42: ='Grant Tracker'!R9 -> 🟢 59 days remaining
A43: ='Grant Tracker'!A10 -> Community Awareness Campaign | B43: ='Grant Tracker'!Q10 -> 46205 | C43: ='Grant Tracker'!R10 -> 🔴 Overdue by 6 days

Sheet Grant Tracker
A1: Grant Tracker — Clean Air Fund India Portfolio (Illustrative)
A2: Note: All figures are illustrative and for demonstration purposes only, based on publicly available information about CAF's India portfolio areas.
A5: Grant Name | B5: Partner | C5: Focus | D5: Total Budget (INR) | E5: Disbursed (INR) | F5: Remaining (INR) | G5: % Utilised | H5: Budget Remaining % | I5: Start Date | J5: End Date | K5: Days Remaining | L5: Progress % | M5: Planned Disbursement | N5: Variance % | O5: Status | P5: Risk | Q5: Reporting Due | R5: Reporting Status | S5: Health Score | T5: Health Rating | U5: Action Required
A6: Air Quality Monitoring | B6: Research Institute | C6: Data and Modelling | D6: 4500000 | E6: 3200000 | F6: =D6-E6 -> 1300000 | G6: =E6/D6 -> 0.71111111 | H6: =F6/D6 -> 0.28888889 | I6: 45748 | J6: 46477 | K6: =J6-TODAY() -> 266 | L6: =MIN(1,MAX(0,(TODAY()-I6)/(J6-I6))) -> 0.6351166 | M6: =D6*L6 -> 2858024.7 | N6: =IF(M6=0,0,(E6-M6)/M6) -> 0.11965443 | O6: On Track | P6: Low | Q6: 46242 | R6: =IF(O6="Completed","✅ Final report submitted",IF((Q6-TODAY())<0,"🔴 Overdue by "&ABS(Q6-TODAY())&" days",IF((Q6-TODAY())<=10,"🟡 Due in "&(Q6-TODAY())&" days","🟢 "&(Q6-TODAY())&" days remaining"))) -> 🟢 31 days remaining | S6: =100-IF(O6="Delayed",20,IF(O6="Needs Attention",10,0))-IF(P6="Medium",15,IF(P6="High",30,0))-IF(AND(O6<>"Completed",(Q6-TODAY())<0),20,0) -> 100 | T6: =IF(S6>=80,"🟢 Green",IF(S6>=50,"🟡 Amber","🔴 Red")) -> 🟢 Green | U6: None — on schedule, monitor next milestone
A7: City Emissions Programme | B7: State Pollution Control Board | C7: Regulatory Implementation | D7: 6800000 | E7: 2100000 | F7: =D7-E7 -> 4700000 | G7: =E7/D7 -> 0.30882353 | H7: =F7/D7 -> 0.69117647 | I7: 45809 | J7: 46356 | K7: =J7-TODAY() -> 145 | L7: =MIN(1,MAX(0,(TODAY()-I7)/(J7-I7))) -> 0.73491773 | M7: =D7*L7 -> 4997440.6 | N7: =IF(M7=0,0,(E7-M7)/M7) -> -0.5797849 | O7: Needs Attention | P7: Medium | Q7: 46220 | R7: =IF(O7="Completed","✅ Final report submitted",IF((Q7-TODAY())<0,"🔴 Overdue by "&ABS(Q7-TODAY())&" days",IF((Q7-TODAY())<=10,"🟡 Due in "&(Q7-TODAY())&" days","🟢 "&(Q7-TODAY())&" days remaining"))) -> 🟡 Due in 9 days | S7: =100-IF(O7="Delayed",20,IF(O7="Needs Attention",10,0))-IF(P7="Medium",15,IF(P7="High",30,0))-IF(AND(O7<>"Completed",(Q7-TODAY())<0),20,0) -> 75 | T7: =IF(S7>=80,"🟢 Green",IF(S7>=50,"🟡 Amber","🔴 Red")) -> 🟡 Amber | U7: Follow up with partner on procurement delays; request revised disbursement timeline
A8: CEO Clean Air Initiative | B8: Civil Society Organisation | C8: Stakeholder Engagement | D8: 1800000 | E8: 1800000 | F8: =D8-E8 -> 0 | G8: =E8/D8 -> 1 | H8: =F8/D8 -> 0 | I8: 45658 | J8: 46203 | K8: =J8-TODAY() -> -8 | L8: =MIN(1,MAX(0,(TODAY()-I8)/(J8-I8))) -> 1 | M8: =D8*L8 -> 1800000 | N8: =IF(M8=0,0,(E8-M8)/M8) -> 0 | O8: Completed | P8: Low | Q8: 46213 | R8: =IF(O8="Completed","✅ Final report submitted",IF((Q8-TODAY())<0,"🔴 Overdue by "&ABS(Q8-TODAY())&" days",IF((Q8-TODAY())<=10,"🟡 Due in "&(Q8-TODAY())&" days","🟢 "&(Q8-TODAY())&" days remaining"))) -> ✅ Final report submitted | S8: =100-IF(O8="Delayed",20,IF(O8="Needs Attention",10,0))-IF(P8="Medium",15,IF(P8="High",30,0))-IF(AND(O8<>"Completed",(Q8-TODAY())<0),20,0) -> 100 | T8: =IF(S8>=80,"🟢 Green",IF(S8>=50,"🟡 Amber","🔴 Red")) -> 🟢 Green | U8: Close out grant file; archive final report
A9: Clean Air & Health Project | B9: Public Health Foundation | C9: Health Impact | D9: 2900000 | E9: 950000 | F9: =D9-E9 -> 1950000 | G9: =E9/D9 -> 0.32758621 | H9: =F9/D9 -> 0.67241379 | I9: 45901 | J9: 46446 | K9: =J9-TODAY() -> 235 | L9: =MIN(1,MAX(0,(TODAY()-I9)/(J9-I9))) -> 0.56880734 | M9: =D9*L9 -> 1649541.3 | N9: =IF(M9=0,0,(E9-M9)/M9) -> -0.42408231 | O9: On Track | P9: Low | Q9: 46270 | R9: =IF(O9="Completed","✅ Final report submitted",IF((Q9-TODAY())<0,"🔴 Overdue by "&ABS(Q9-TODAY())&" days",IF((Q9-TODAY())<=10,"🟡 Due in "&(Q9-TODAY())&" days","🟢 "&(Q9-TODAY())&" days remaining"))) -> 🟢 59 days remaining | S9: =100-IF(O9="Delayed",20,IF(O9="Needs Attention",10,0))-IF(P9="Medium",15,IF(P9="High",30,0))-IF(AND(O9<>"Completed",(Q9-TODAY())<0),20,0) -> 100 | T9: =IF(S9>=80,"🟢 Green",IF(S9>=50,"🟡 Amber","🔴 Red")) -> 🟢 Green | U9: None — early implementation phase, on pace
A10: Community Awareness Campaign | B10: Urban Local Body | C10: Citizen Engagement | D10: 1200000 | E10: 40000 | F10: =D10-E10 -> 1160000 | G10: =E10/D10 -> 0.033333333 | H10: =F10/D10 -> 0.96666667 | I10: 45931 | J10: 46295 | K10: =J10-TODAY() -> 84 | L10: =MIN(1,MAX(0,(TODAY()-I10)/(J10-I10))) -> 0.76923077 | M10: =D10*L10 -> 923076.92 | N10: =IF(M10=0,0,(E10-M10)/M10) -> -0.95666667 | O10: Delayed | P10: High | Q10: 46205 | R10: =IF(O10="Completed","✅ Final report submitted",IF((Q10-TODAY())<0,"🔴 Overdue by "&ABS(Q10-TODAY())&" days",IF((Q10-TODAY())<=10,"🟡 Due in "&(Q10-TODAY())&" days","🟢 "&(Q10-TODAY())&" days remaining"))) -> 🔴 Overdue by 6 days | S10: =100-IF(O10="Delayed",20,IF(O10="Needs Attention",10,0))-IF(P10="Medium",15,IF(P10="High",30,0))-IF(AND(O10<>"Completed",(Q10-TODAY())<0),20,0) -> 30 | T10: =IF(S10>=80,"🟢 Green",IF(S10>=50,"🟡 Amber","🔴 Red")) -> 🔴 Red | U10: Urgent check-in call; missed milestone, request cause and revised plan
A11: Total / Portfolio | D11: =SUM(D6:D10) -> 17200000 | E11: =SUM(E6:E10) -> 8090000 | F11: =SUM(F6:F10) -> 9110000 | G11: =E11/D11 -> 0.47034884 | H11: =F11/D11 -> 0.52965116

Sheet Finance & Deliverables
A1: Finance & Deliverables Tracker
A2: Note: Illustrative payment and deliverable records, linked to Grant Tracker figures.
A4: Grant Name | B4: Payment Request Submitted | C4: Payment Approved | D4: Invoice Received | E4: Invoice Pending | F4: Payment Date | G4: Actual Payment (INR) | H4: Expected Payment (INR) | I4: Payment Variance (INR) | J4: Deliverables Planned | K4: Deliverables Completed | L4: Completion % | M4: Milestones Achieved | N4: Next Milestone
A5: Air Quality Monitoring | B5: 46174 | C5: 46183 | D5: Yes | E5: No | F5: 46191 | G5: 3200000 | H5: ='Grant Tracker'!E6 -> 3200000 | I5: =G5-H5 -> 0 | J5: 6 | K5: 4 | L5: =K5/J5 -> 0.66666667 | M5: Sensor network live in 3 cities | N5: Mid-term data validation report
A6: City Emissions Programme | B6: 46188 | D6: Yes | E6: Yes | G6: 2100000 | H6: ='Grant Tracker'!E7 -> 2100000 | I6: =G6-H6 -> 0 | J6: 5 | K6: 2 | L6: =K6/J6 -> 0.4 | M6: Baseline emissions inventory | N6: Draft state implementation roadmap
A7: CEO Clean Air Initiative | B7: 46178 | C7: 46185 | D7: Yes | E7: No | F7: 46193 | G7: 1800000 | H7: ='Grant Tracker'!E8 -> 1800000 | I7: =G7-H7 -> 0 | J7: 4 | K7: 4 | L7: =K7/J7 -> 1 | M7: All CEO roundtables completed | N7: Final report submitted
A8: Clean Air & Health Project | B8: 46193 | C8: 46201 | D8: Yes | E8: No | F8: 46205 | G8: 950000 | H8: ='Grant Tracker'!E9 -> 950000 | I8: =G8-H8 -> 0 | J8: 5 | K8: 2 | L8: =K8/J8 -> 0.4 | M8: Health impact baseline survey | N8: Household exposure pilot results
A9: Community Awareness Campaign | B9: 46162 | D9: No | E9: Yes | G9: 40000 | H9: ='Grant Tracker'!E10 -> 40000 | I9: =G9-H9 -> 0 | J9: 4 | K9: 1 | L9: =K9/J9 -> 0.25 | M9: Campaign launch event | N9: Revised outreach plan (overdue)
